dqb2/__init__.py
dqb2/__version__.py
dqb2/_imports_.py
dqb2/dash_query_builder.py
dqb2/dqb2.js
dqb2/main.css
dqb2/metadata.json
dqb2/package-info.json
dqb2-1.0.19.dist-info/LICENSE
dqb2-1.0.19.dist-info/METADATA
dqb2-1.0.19.dist-info/WHEEL
dqb2-1.0.19.dist-info/top_level.txt
dqb2-1.0.19.dist-info/RECORD
