Metadata-Version: 2.2
Name: dqb2
Version: 1.0.19
Summary: A fork from dash-query-builder
Author: Mohamed El-Deeb <s-mohamed.eldeeb@zewailcity.edu.eg>
Author-email: Mohamed El-Deeb <s-mohamed.eldeeb@zewailcity.edu.eg>
License: MIT
Project-URL: Homepage, https://github.com/mhdeeb/dash-query-builder-2
Project-URL: Issues, https://github.com/mhdeeb/dash-query-builder-2/issues
Classifier: Programming Language :: Python :: 3
Requires-Python: >=3.8
License-File: LICENSE
Requires-Dist: build>=1.2.2.post1
Requires-Dist: dash[dev]>=2.5.1
Requires-Dist: twine>=6.1.0
Requires-Dist: wheel>=0.45.1
Dynamic: author
